pyticcom/__init__.py
pyticcom/const.py
pyticcom/scanner.py
pyticcom/teleinfo.py
pyticcom-1.2.dist-info/LICENSE
pyticcom-1.2.dist-info/METADATA
pyticcom-1.2.dist-info/WHEEL
pyticcom-1.2.dist-info/top_level.txt
pyticcom-1.2.dist-info/RECORD
