Metadata-Version: 2.1
Name: pyticcom
Version: 1.2
Summary: Teleinfo python library
Home-page: https://github.com/biker91620/pyticcom/tree/master
Author: biker91620
License: GPL-3
Keywords: rest,pyticcom,linky,tic,io,smart-things,iot
Platform: UNKNOWN
Classifier: Programming Language :: Python
Classifier: Development Status :: 5 - Production/Stable
Classifier: License :: OSI Approved :: GNU General Public License v3 or later (GPLv3+)
Classifier: Programming Language :: Python :: 3
Classifier: Programming Language :: Python :: 3.5
Classifier: Programming Language :: Python :: 3.6
Classifier: Programming Language :: Python :: 3.7
Classifier: Intended Audience :: Developers
Classifier: Intended Audience :: System Administrators
Classifier: Topic :: Home Automation
Requires-Dist: requests (>=2)
